MANIFEST.in
README
requirements.txt
setup.py
ajenti.plugin.dashboard.egg-info/PKG-INFO
ajenti.plugin.dashboard.egg-info/SOURCES.txt
ajenti.plugin.dashboard.egg-info/dependency_links.txt
ajenti.plugin.dashboard.egg-info/requires.txt
ajenti.plugin.dashboard.egg-info/top_level.txt
ajenti_plugin_dashboard/README.md
ajenti_plugin_dashboard/__init__.py
ajenti_plugin_dashboard/api.py
ajenti_plugin_dashboard/bower.json
ajenti_plugin_dashboard/main.py
ajenti_plugin_dashboard/plugin.yml
ajenti_plugin_dashboard/requirements.txt
ajenti_plugin_dashboard/views.py
ajenti_plugin_dashboard/locale/app.pot
ajenti_plugin_dashboard/locale/af/LC_MESSAGES/app.js
ajenti_plugin_dashboard/locale/af/LC_MESSAGES/app.po
ajenti_plugin_dashboard/locale/af/LC_MESSAGES/app.po~
ajenti_plugin_dashboard/locale/ar/LC_MESSAGES/app.js
ajenti_plugin_dashboard/locale/ar/LC_MESSAGES/app.po
ajenti_plugin_dashboard/locale/ar/LC_MESSAGES/app.po~
ajenti_plugin_dashboard/locale/be/LC_MESSAGES/app.js
ajenti_plugin_dashboard/locale/be/LC_MESSAGES/app.po
ajenti_plugin_dashboard/locale/be/LC_MESSAGES/app.po~
ajenti_plugin_dashboard/locale/bg/LC_MESSAGES/app.js
ajenti_plugin_dashboard/locale/bg/LC_MESSAGES/app.po
ajenti_plugin_dashboard/locale/bg/LC_MESSAGES/app.po~
ajenti_plugin_dashboard/locale/bn/LC_MESSAGES/app.js
ajenti_plugin_dashboard/locale/bn/LC_MESSAGES/app.po
ajenti_plugin_dashboard/locale/bn/LC_MESSAGES/app.po~
ajenti_plugin_dashboard/locale/bs/LC_MESSAGES/app.js
ajenti_plugin_dashboard/locale/bs/LC_MESSAGES/app.po
ajenti_plugin_dashboard/locale/ca/LC_MESSAGES/app.js
ajenti_plugin_dashboard/locale/ca/LC_MESSAGES/app.po
ajenti_plugin_dashboard/locale/ca/LC_MESSAGES/app.po~
ajenti_plugin_dashboard/locale/cs/LC_MESSAGES/app.js
ajenti_plugin_dashboard/locale/cs/LC_MESSAGES/app.po
ajenti_plugin_dashboard/locale/cs/LC_MESSAGES/app.po~
ajenti_plugin_dashboard/locale/da/LC_MESSAGES/app.js
ajenti_plugin_dashboard/locale/da/LC_MESSAGES/app.po
ajenti_plugin_dashboard/locale/da/LC_MESSAGES/app.po~
ajenti_plugin_dashboard/locale/de/LC_MESSAGES/app.js
ajenti_plugin_dashboard/locale/de/LC_MESSAGES/app.po
ajenti_plugin_dashboard/locale/de/LC_MESSAGES/app.po~
ajenti_plugin_dashboard/locale/el/LC_MESSAGES/app.js
