Metadata-Version: 1.2
Name: ajenti.plugin.dashboard
Version: 0.41
Summary: Dashboard
Home-page: https://ajenti.org
Author: Ajenti project
Author-email: e@ajenti.org
License: UNKNOWN
Platform: UNKNOWN
Requires-Python: >=3
